LICENSE
README.md
setup.py
cv2/__init__.py
cv2/core.py
cvvv2.egg-info/PKG-INFO
cvvv2.egg-info/SOURCES.txt
cvvv2.egg-info/dependency_links.txt
cvvv2.egg-info/top_level.txt
tests/__init__.py
tests/test_fakecv2.py