Metadata-Version: 2.1
Name: cvvv2
Version: 4.5.5
Summary: A fake OpenCV package for Python used in security awareness training
Home-page: https://visionlab-security.org/cv2-awareness
Author: VisionLab Research
Author-email: contact@visionlab-security.org
License: MIT
Classifier: Programming Language :: Python :: 3
Classifier: License :: OSI Approved :: MIT License
Classifier: Operating System :: OS Independent
Classifier: Topic :: Security
Classifier: Development Status :: 4 - Beta
Classifier: Intended Audience :: Developers
Requires-Python: >=3.6
License-File: LICENSE
